Workbook

Sheet BOM
A1: Bill of Materials – electric single-motor fixed-wing RC aircraft (1.1 m span, high wing)
A2: Recommendation 1 = Budget option, Recommendation 2 = Performance option. No parts purchased. Prices are approximate INR (incl. GST) – see Sources sheet for which are listing-based vs estimated; re-check before ordering.
A3: Blue = hardcoded input/price, black = formula. Link text states whether the link is a product page or a store search.
A5: ID | B5: Category | C5: Component | D5: Recommendation 1 (Budget) | E5: Recommendation 2 (Performance) | F5: Key specifications | G5: Quantity | H5: Unit price R1 (₹) | I5: Unit price R2 (₹) | J5: Estimated cost R1 (₹) | K5: Estimated cost R2 (₹) | L5: Installed mass R1 (g) | M5: Installed mass R2 (g) | N5: Source R1 | O5: Source R2 | P5: Notes
A6: A1 | B6: Airframe | C6: Foam sheet (wing, fuselage, tail) | D6: 5 mm foam-core (Kapa) board, A1 sheet | E6: 6 mm Depron-type XPS foam sheet | F6: ~0.86 m² of structure; foam-glue friendly; qty includes ~30% cutting waste | G6: 3 | H6: 200 | I6: 350 | J6: =G6*H6 -> 600 | K6: =G6*I6 -> 1050 | L6: =Calcs!B9*Calcs!B10*1000 -> 258 | M6: =Calcs!C9*Calcs!C10*1000 -> 172 | N6: Amazon.in – search | O6: Amazon.in – search | P6: Estimated prices. Depron-type sheets are less common in India; check local hobby shops.
A7: A2 | B7: Airframe | C7: Main wing spar | D7: 6 mm solid carbon rod, 1 m | E7: 8x6 mm carbon tube, 1 m | F7: Bending stiffness EI dominates; see Calcs spar check | G7: 1 | H7: 300 | I7: 650 | J7: =G7*H7 -> 300 | K7: =G7*I7 -> 650 | L7: 45 | M7: 35 | N7: Amazon.in – search | O7: Amazon.in – search | P7: Estimated. Tube is lighter and ~2x stiffer than the rod.
A8: A3 | B8: Airframe | C8: Fuselage / tail stiffeners | D8: 3 mm bamboo skewers (pack) | E8: 3 mm carbon rod, 1 m | F8: Longerons, tail-boom reinforcement | G8: 1 | H8: 40 | I8: 300 | J8: =G8*H8 -> 40 | K8: =G8*I8 -> 300 | L8: 10 | M8: 12 | N8: Amazon.in – search | O8: Amazon.in – search | P8: Estimated.
A9: A4 | B9: Airframe | C9: Landing gear (optional – ground takeoff) | D9: 3 mm steel wire main gear + 55 mm foam wheels | E9: Pre-bent aluminium gear + 65 mm wheels + tail wheel | F9: Not needed if hand-launched and belly-landed | G9: 1 | H9: 350 | I9: 900 | J9: =G9*H9 -> 350 | K9: =G9*I9 -> 900 | L9: 40 | M9: 51 | N9: Amazon.in – search | O9: Amazon.in – search | P9: Estimated. Can be skipped (see Budget sheet).
A10: P1 | B10: Propulsion | C10: Brushless motor | D10: A2212 1000 KV outrunner | E10: SunnySky X2212 ~980 KV | F10: 2-3S, ~160 W class, 28 mm can, cross mount + prop adapter included; max ~15-18 A | G10: 1 | H10: 375 | I10: 1700 | J10: =G10*H10 -> 375 | K10: =G10*I10 -> 1700 | L10: 58 | M10: 60 | N10: Robu – product page | O10: Amazon.in – search | P10: R1 price: Robu listing Rs 375 (page showed out-of-stock when checked; verify). R2 estimated.
A11: P2 | B11: Propulsion | C11: ESC (electronic speed controller) | D11: SimonK 30 A ESC (with BEC) | E11: Hobbywing Skywalker 40 A V2 (with BEC) | F11: Continuous current, 2-4S, 5 V BEC for Rx + servos | G11: 1 | H11: 342 | I11: 1700 | J11: =G11*H11 -> 342 | K11: =G11*I11 -> 1700 | L11: 26 | M11: 35 | N11: Robu – search | O11: Amazon.in – search | P11: R1 price: Robu listing Rs 342 (without connectors). R2 estimated.
A12: P3 | B12: Propulsion | C12: Propeller (1 mounted + 2 spare) | D12: 10x4.7 slow-fly nylon prop | E12: APC-style 10x4.7 SF prop | F12: Dia 10 in, pitch 4.7 in; spares for crashes | G12: 3 | H12: 90 | I12: 450 | J12: =G12*H12 -> 270 | K12: =G12*I12 -> 1350 | L12: 13 | M12: 14 | N12: Amazon.in – search | O12: Amazon.in – search | P12: Estimated. Mass is for the mounted prop only.
A13: P4 | B13: Propulsion | C13: LiPo battery | D13: Orange 3S 2200 mAh 30C | E13: Orange 3S 2200 mAh 40C | F13: 11.1 V nominal, XT60; capacity vs mass trade-off in Calcs | G13: 1 | H13: 1450 | I13: 1750 | J13: =G13*H13 -> 1450 | K13: =G13*I13 -> 1750 | L13: 185 | M13: 190 | N13: Robu – product page | O13: Robu – category | P13: Estimated prices – check live listing.
A14: R1 | B14: Radio & control | C14: Transmitter | D14: FlySky FS-i6X (AFHDS 2A) | E14: RadioMaster Pocket (ELRS 2.4 GHz) | F14: 6+ channels; mixing for ailerons/failsafe | G14: 1 | H14: 4600 | I14: 10500 | J14: =G14*H14 -> 4600 | K14: =G14*I14 -> 10500 | L14: 0 | M14: 0 | N14: Robu – product page | O14: Amazon.in – search | P14: R1: Robu/Probots sell Tx+Rx bundles (Rs ~5,500 total in this BOM). R2 estimated.
A15: R2 | B15: Radio & control | C15: Receiver | D15: FlySky FS-iA6B (AFHDS 2A, 6 ch) | E15: RadioMaster ER6 (ELRS, 6 ch PWM) | F15: Must match transmitter protocol; PWM out for servos/ESC | G15: 1 | H15: 900 | I15: 1300 | J15: =G15*H15 -> 900 | K15: =G15*I15 -> 1300 | L15: 15 | M15: 6 | N15: Probots – product page (bundle) | O15: Amazon.in – search | P15: Estimated. Bundle page lists Tx + iA10B; iA6B also AFHDS 2A.
A16: R3 | B16: Radio & control | C16: Servos (2 aileron, elevator, rudder) | D16: SG90 9 g plastic-gear micro servo | E16: MG90S 9 g metal-gear micro servo | F16: 4.8-6 V, ~1.6-2 kgf.cm; hinge moments << stall torque | G16: 4 | H16: 110 | I16: 260 | J16: =G16*H16 -> 440 | K16: =G16*I16 -> 1040 | L16: 36 | M16: 54 | N16: Amazon.in – search | O16: Amazon.in – search | P16: Estimated.
A17: W1 | B17: Assembly | C17: Control linkage (pushrods, horns, clevises) | D17: 1.5 mm wire pushrods + nylon horns + clevises | E17: 1 mm carbon pushrods + CNC horns + metal clevises | F17: 4 sets | G17: 1 | H17: 250 | I17: 600 | J17: =G17*H17 -> 250 | K17: =G17*I17 -> 600 | L17: 18 | M17: 15 | N17: Amazon.in – search | O17: Amazon.in – search | P17: Estimated.
A18: W2 | B18: Assembly | C18: Hinges & surface finish | D18: Clear + coloured packing tape (tape hinges) | E18: Heat-shrink covering film + CA hinges | F18: Tape hinges: cheap, repairable; film: lighter finish, better moisture/impact resistance | G18: 1 | H18: 150 | I18: 1400 | J18: =G18*H18 -> 150 | K18: =G18*I18 -> 1400 | L18: 25 | M18: 60 | N18: Amazon.in – search | O18: Amazon.in – search | P18: Estimated.
... A27: G4 | B27: Ground support | C27: Spares kit | D27: 1 spare servo + 1 foam sheet + glue | E27: 1 spare servo + 1 foam sheet + glue | F27: Quick repair between flights | G27: 1 | H27: 400 | I27: 700 | J27: =G27*H27 -> 400 | K27: =G27*I27 -> 700 | L27: 0 | M27: 0 | N27: Robu – search | O27: Amazon.in – search | P27: Estimated.
C29: Aircraft-only total (excl. ground support) | J29: =SUM(J6:J27)-SUMIF($B$6:$B$27,"Ground support",J6:J27) -> 11017 | K29: =SUM(K6:K27)-SUMIF($B$6:$B$27,"Ground support",K6:K27) -> 26640 | L29: =SUM(L6:L27) -> 827 | M29: =SUM(M6:M27) -> 802 | N29: ← installed mass total (g), before 5% contingency
C30: Ground support total | J30: =SUMIF($B$6:$B$27,"Ground support",J6:J27) -> 3400 | K30: =SUMIF($B$6:$B$27,"Ground support",K6:K27) -> 7300
C31: GRAND TOTAL | J31: =J29+J30 -> 14417 | K31: =K29+K30 -> 33940

Sheet Budget
A1: Part D – Budget, configurations and selection
A3: Category | B3: Budget config (₹) | C3: Performance config (₹)
A4: Airframe | B4: =SUMIF(BOM!$B$6:$B$27,A4,BOM!$J$6:$J$27) -> 1290 | C4: =SUMIF(BOM!$B$6:$B$27,A4,BOM!$K$6:$K$27) -> 2900
A5: Propulsion | B5: =SUMIF(BOM!$B$6:$B$27,A5,BOM!$J$6:$J$27) -> 2437 | C5: =SUMIF(BOM!$B$6:$B$27,A5,BOM!$K$6:$K$27) -> 6500
A6: Radio & control | B6: =SUMIF(BOM!$B$6:$B$27,A6,BOM!$J$6:$J$27) -> 5940 | C6: =SUMIF(BOM!$B$6:$B$27,A6,BOM!$K$6:$K$27) -> 12840
A7: Assembly | B7: =SUMIF(BOM!$B$6:$B$27,A7,BOM!$J$6:$J$27) -> 1350 | C7: =SUMIF(BOM!$B$6:$B$27,A7,BOM!$K$6:$K$27) -> 4400
A8: Ground support | B8: =SUMIF(BOM!$B$6:$B$27,A8,BOM!$J$6:$J$27) -> 3400 | C8: =SUMIF(BOM!$B$6:$B$27,A8,BOM!$K$6:$K$27) -> 7300
A9: Aircraft subtotal (first four categories) | B9: =SUM(B4:B7) -> 11017 | C9: =SUM(C4:C7) -> 26640
A10: Ground support subtotal | B10: =B8 -> 3400 | C10: =C8 -> 7300
A11: Total build cost | B11: =B9+B10 -> 14417 | C11: =C9+C10 -> 33940
A12: Price-volatility contingency (10%) | B12: =B11*0.1 -> 1441.7 | C12: =C11*0.1 -> 3394
A13: Total with contingency | B13: =B11+B12 -> 15858.7 | C13: =C11+C12 -> 37334
A15: Configuration comparison
A16: Takeoff mass (g) | B16: =Calcs!B13 -> 868.35 | C16: =Calcs!C13 -> 842.1
A17: Wing loading (g/dm²) | B17: =Calcs!B16 -> 35.882231 | C17: =Calcs!C16 -> 34.797521
A18: Static thrust-to-weight | B18: =Calcs!B31 -> 0.80612656 | C18: =Calcs!C31 -> 1.0093813
A19: Stall speed (m/s) | B19: =Calcs!B19 -> 7.2281114 | C19: =Calcs!C19 -> 7.118021
A20: Rate of climb (m/s) | B20: =Calcs!B53 -> 1.8320247 | C20: =Calcs!C53 -> 2.5975849
A21: Mixed-flying endurance (min) | B21: =Calcs!B49 -> 15.085714 | C21: =Calcs!C49 -> 15.085714
A22: ESC margin (x) | B22: =Calcs!B35 -> 2.1428571 | C22: =Calcs!C35 -> 2.8571429
A23: Spar safety factor at 3 g (x) | B23: =Calcs!B65 -> 4.2657782 | C23: =Calcs!C65 -> 7.1276063
A24: Propulsion verdict | B24: =Calcs!B55 -> PASS | C24: =Calcs!C55 -> PASS
A25: Extra cost of Performance over Budget (₹, aircraft + ground) | C25: =C11-B11 -> 19523
A26: Thrust-to-weight gain per ₹1,000 extra | C26: =(C18-B18)/(C25/1000) -> 0.010411041
A28: Safe cost-saving opportunities (apply to Budget config)
A29: Opportunity | B29: Saving (₹) | C29: Why it is safe / condition
A30: Borrow a club transmitter (buy only the matching receiver) | B30: =BOM!J14 -> 4600 | C30: Radio is ground equipment; only the receiver must match the protocol. Condition: club Tx is AFHDS 2A (or buy matching Rx).
A31: Use club charger, watt meter and LiPo bag | B31: =BOM!J24+BOM!J25+BOM!J26 -> 3000 | C31: Shared tools; still must balance-charge in a LiPo bag, supervised.
A32: Hand launch + belly landing (omit landing gear) | B32: =BOM!J9 -> 350 | C32: Allowed by brief; also saves ~40 g and drag. Foam belly is repairable. Needs a hand-launch-safe T/W (>=0.6).
A33: Use lab stock for tape and wire | B33: =BOM!J18+BOM!J21 -> 300 | C33: Non-critical consumables; keep power leads >= 14 AWG.
A34: Foam-core board instead of Depron-type XPS (already in Budget config) | B34: =BOM!K6-BOM!J6 -> 450 | C34: Cheaper and locally available; costs ~86 g of extra mass.
A35: SG90 instead of MG90S servos (already in Budget config) | B35: =BOM!K16-BOM!J16 -> 600 | C35: Hinge torque needs << 1 kgf.cm; upgrade to MG90S if gears strip in testing.
A36: Lean budget total after the first four optional savings (₹) | B36: =B11-SUM(B30:B33) -> 6167
A37: Do NOT cut: ESC current margin, LiPo bag/balance charging, spar, spare props/servo, range check. These protect against fire, loss of control and rebuild time.
A39: Decision matrix (weights are judgement inputs)
A40: Criterion (weight) | B40: Budget score (1-5) | C40: Performance score (1-5) | D40: Weight
A41: Cost | B41: 5 | C41: 2 | D41: 0.3
A42: Repairability / spares per ₹ | B42: 5 | C42: 3 | D42: 0.2
A43: Performance margin | B43: 3 | C43: 4 | D43: 0.2
A44: Local availability / lead time | B44: 5 | C44: 3 | D44: 0.15
A45: Reliability risk (clone parts, imports) | B45: 3 | C45: 4 | D45: 0.15
A46: Weighted score | B46: =SUMPRODUCT($D$41:$D$45,B41:B45) -> 4.3 | C46: =SUMPRODUCT($D$41:$D$45,C41:C45) -> 3.05 | D46: =SUM(D41:D45) -> 1
A47: Selected configuration | B47: =IF(B46>=C46,"Budget","Performance") -> Budget
A49: Selected: BUDGET configuration. Justification: (1) By the Calcs sheet it already passes every propulsion check (static T/W ~0.8, ESC margin ~2.1x, battery margin ~4.7x, spar SF > 4) so the extra ~₹19,500 of the Performance build buys only a ~0.2 T/W gain, ~25 g less mass and no extra mixed-flight endurance (same 2200 mAh pack). (2) Foam aircraft crash; money saved is better spent on spare foam, props and servos (included) so the team can fly again within hours. (3) Every Budget part is stocked by Indian vendors (Robu, Probots, Amazon.in), avoiding import delays for Depron/ELRS parts. (4) Main risks of the Budget set (clone ESC, plastic-gear servos, optimistic C ratings) are controlled by testing: thrust/current rig test, range check, and one-line upgrades (MG90S ≈ +₹150×4, 40C pack) if tests show a problem.

Sheet Rationale
A1: Part C – Technical justification (numbers refer to the Calcs sheet; all inputs there are editable)
A3: Topic | B3: Reasoning
A4: Aircraft concept & assumptions | B4: High-wing, conventional-tail trainer, 1.10 m span x 0.22 m mean chord (S ≈ 0.24 m², AR 5), single tractor motor, ailerons + elevator + rudder + throttle (4 control channels + throttle). Assumptions: sea-level air, foam airframe built to ~0.86 m² of skin area, 3S LiPo, CLmax 1.1, cruise L/D 6, 80% usable battery. Estimated takeoff mass ≈ 0.87 kg (budget) / 0.84 kg (performance); wing loading ≈ 36 g/dm²; stall speed ≈ 7 m/s.
A5: C1. Motor–propeller match & thrust check | B5: A2212 1000 KV on 3S (11.1 V) spins ≈ 11,100 rpm unloaded, ≈ 8,900 rpm loaded (assume 80%). A 10x4.7 slow-fly prop gives a pitch speed ≈ 17.7 m/s – about 2.4x the stall speed, so thrust is still useful at climb/cruise speed – and a static thrust near 700 g at ≈ 14 A (≈ 155 W, at the motor’s ~160 W rating, so avoid long full-throttle runs). Sellers also list 10x6 / 9x5 as suitable props; the lower-pitch 10x4.7 is chosen for hand-launch static thrust at lower current. Thrust-check method: (1) bench: clamp motor, ESC, prop and battery on a rig, hang or lever it against a kitchen scale / load cell, run full throttle for ≤ 10 s in short bursts, log thrust, amps (watt meter), volts and motor temperature; (2) accept if static T/W ≥ 0.6 (hand launch) and preferably ≥ 0.8, current ≤ 80% of ESC rating, voltage sag < 10%, motor/ESC < 70 °C; (3) cross-check against a propulsion calculator such as eCalc; (4) flight: confirm a steady climb with throttle in reserve.
A6: C2. ESC rating & electrical margin | B6: Full-throttle current ≈ 14 A (assumed; verify). Prop changes (10x6 ≈ 17–18 A), a warm battery and stall transients argue for ≥ 1.5–2x margin, so a 30 A ESC (≈ 2.1x) is the budget choice and 40 A (≈ 2.9x) the performance choice. Also check: 3S (12.6 V) is within the ESC’s 2–4S range; BEC must supply 5 V for the receiver + four servos (peak ≈ 1 A, average ≈ 0.3 A) – a linear BEC on 3S dissipates (12.6–5) × I, so if the ESC runs hot with all servos loaded add an external UBEC. Calibrate throttle endpoints, disable brake and set battery cut-off for 3S.
A7: C3. Battery selection & trade-offs | B7: 3S matches the motor KV/prop pairing (pack voltage sets rpm). 2200 mAh 30C: usable ≈ 1.76 Ah; continuous capability 2.2 Ah × 30C = 66 A vs ≈ 14 A demand (≈ 4.7x) even if the C rating is optimistic. Planned mixed flying (≈ 7 A average) gives ≈ 15 min; steady cruise alone ≈ 34 min (optimistic upper bound). Trade-offs (Calcs table): 1500 mAh saves ≈ 60 g (higher T/W, lower wing loading) but shortens mixed flights to ≈ 10 min; 3000 mAh adds ≈ 60 g and raises wing loading and stall speed for ≈ 20 min. 2200 mAh balances endurance and mass for a ~0.9 kg foam trainer. Use XT60 connectors, a balance charger, storage at ~3.8 V/cell, and a LiPo bag. Battery position is the main CG-trim tool.
A8: C4. Servo count & control surfaces | B8: Four 9 g servos: two ailerons (one per wing, separate servos so they can be differenced/mixed or driven through a Y-harness), one elevator, one rudder. Throttle goes directly to the ESC. Hinge-moment check: dynamic pressure at a 20 m/s dive ≈ 245 Pa; a 0.3 x 0.06 m elevator with a conservative hinge-moment coefficient of 0.1 needs < 0.3 kgf·cm, versus ≈ 1.6 kgf·cm servo stall torque (SG90 class) – margin > 5x. Metal-gear MG90S is the upgrade where crash/strip-out loads matter.
A9: C5. Structural material | B9: Foam-core board (Budget) is cheapest, locally available and repairable with hot glue/tape in minutes, but heavier (~0.30 kg/m²). Depron-type XPS (Performance) is ~1/3 lighter but costs more and is harder to source in India. Local carbon reinforcement only where needed: main spar (Calcs: 3 g bending stress ≈ 140 MPa for the 6 mm rod, SF > 4 even ignoring foam skins; the 8x6 mm tube ≈ 2x stiffer and lighter) and optional 3 mm carbon longerons. Balsa is lightest per stiffness but fragile and slower to repair; EPP is tough but needs moulds/imports; full composites are costly and hard to repair. Scores below.
A10: C6. Compatibility checks | B10: Electrical: pack voltage 3S (≤ 12.6 V) ≤ ESC and motor limits; XT60 battery ↔ ESC; 3.5 mm bullets motor ↔ ESC; ESC 3-wire lead into the throttle channel of the receiver (BEC 5 V powers Rx/servos); servos 4.8–6 V; wire gauge ≥ 14 AWG for power leads; check motor spins the right way (swap any two phases). Mechanical: motor can 28 mm and cross-mount 16/19 mm pattern vs firewall; prop adapter bore vs shaft diameter (vendors list 3.17 vs 3.7 mm – confirm); 127 mm prop radius vs ground/fuselage clearance; servo arm/horn throw geometry; CG 25–33% of mean chord (≈ 55–73 mm behind leading edge) set by moving the battery. Transmitter–receiver: FlySky FS-i6X (AFHDS 2A) with FS-iA6B/iA10B (AFHDS 2A) – same protocol, bind by holding the BIND key while powering the Tx; set throttle-cut failsafe; at least 5 channels. The ELRS alternative needs an ELRS receiver on a compatible firmware major version and the same binding phrase. Before first flight: range check at ~30 m with reduced power, control-direction check, and motor test with the prop fitted only after a bench run.
A12: Structural material scoring (1-5, 5 = best; weights are inputs)
A13: Material | B13: Mass | C13: Strength/stiffness | D13: Cost | E13: Repairability | F13: Weighted score
A14: Weight | B14: 0.3 | C14: 0.2 | D14: 0.25 | E14: 0.25
A15: Foam-core (Kapa) board + CF spar | B15: 2 | C15: 3 | D15: 5 | E15: 5 | F15: =SUMPRODUCT($B$14:$E$14,B15:E15) -> 3.7
A16: Depron/XPS foam + CF spar | B16: 4 | C16: 3 | D16: 4 | E16: 4 | F16: =SUMPRODUCT($B$14:$E$14,B16:E16) -> 3.8
A17: Balsa/ply built-up + film | B17: 5 | C17: 4 | D17: 2 | E17: 3 | F17: =SUMPRODUCT($B$14:$E$14,B17:E17) -> 3.55
A18: EPP/EPO foam | B18: 4 | C18: 3 | D18: 3 | E18: 5 | F18: =SUMPRODUCT($B$14:$E$14,B18:E18) -> 3.8
A19: Carbon/glass composite shell | B19: 5 | C19: 5 | D19: 1 | E19: 1 | F19: =SUMPRODUCT($B$14:$E$14,B19:E19) -> 3
A20: 3D-printed LW-PLA | B20: 3 | C20: 3 | D20: 3 | E20: 2 | F20: =SUMPRODUCT($B$14:$E$14,B20:E20) -> 2.75
A22: Scores are judgement-based; the foam-core board build is selected for the competition on cost and repairability, with Depron-type foam the lighter alternative.

Sheet Calcs
A1: Calculations & assumptions – RC aircraft (blue = input/assumption, black = formula)
A3: Parameter | B3: Budget config | C3: Performance config | D3: Unit | E3: Note / basis
A4: GEOMETRY, MASS AND WING LOADING
A5: Wingspan | B5: 1.1 | C5: 1.1 | D5: m | E5: Brief: 1-1.2 m. Assumed high-wing, flat-bottom foam wing.
A6: Mean chord | B6: 0.22 | C6: 0.22 | D6: m | E6: Assumed -> aspect ratio ~5 (docile trainer).
A7: Wing area | B7: =B5*B6 -> 0.242 | C7: =C5*C6 -> 0.242 | D7: m² | E7: b x c
A8: Aspect ratio | B8: =B5^2/B7 -> 5 | C8: =C5^2/C7 -> 5 | D8: - | E8: b²/S
A9: Foam area used (wing 2 surfaces + fuselage + tail) | B9: 0.86 | C9: 0.86 | D9: m² | E9: Assumed build: wing 0.44 + fuselage 0.30 + tail 0.12 m².
A10: Foam areal density | B10: 0.3 | C10: 0.2 | D10: kg/m² | E10: Assumed: 5 mm foam-core board incl. paper skins ~0.30; 6 mm Depron-type XPS ~0.20. Weigh a sheet to confirm.
A11: Dry mass of flying items (from BOM) | B11: =SUM(BOM!L6:L27) -> 827 | C11: =SUM(BOM!M6:M27) -> 802 | D11: g | E11: Sum of installed masses in BOM (ground-support items = 0 g).
A12: Contingency (paint, CG trim, extra glue) | B12: 0.05 | C12: 0.05 | D12: fraction | E12: Assumed 5%.
A13: Estimated takeoff mass | B13: =B11*(1+B12) -> 868.35 | C13: =C11*(1+C12) -> 842.1 | D13: g | E13: Bonus: takeoff mass.
A14: Gravitational acceleration | B14: 9.81 | C14: 9.81 | D14: m/s²
A15: Takeoff weight | B15: =B13/1000*B14 -> 8.5185135 | C15: =C13/1000*C14 -> 8.261001 | D15: N
A16: Wing loading | B16: =B13/(B7*100) -> 35.882231 | C16: =C13/(C7*100) -> 34.797521 | D16: g/dm² | E16: Trainer range ~20-40 g/dm².
A17: Air density | B17: 1.225 | C17: 1.225 | D17: kg/m³ | E17: ISA sea level (use ~1.0-1.1 at high-altitude sites; reduces thrust and lift).
A18: Wing CL,max | B18: 1.1 | C18: 1.1 | D18: - | E18: Conservative for a thin cambered foam wing at low Re.
A19: Stall speed | B19: =SQRT(2*B15/(B17*B7*B18)) -> 7.2281114 | C19: =SQRT(2*C15/(C17*C7*C18)) -> 7.118021 | D19: m/s | E19: Vs = sqrt(2W / (rho S CLmax))
A20: Cruise speed | B20: =1.5*B19 -> 10.842167 | C20: =1.5*C19 -> 10.677032 | D20: m/s | E20: Assumed 1.5 x Vs.
A21: PROPULSION & ELECTRICAL
A22: Battery cells (S) | B22: 3 | C22: 3 | D22: - | E22: 3S LiPo.
A23: Nominal pack voltage | B23: =B22*3.7 -> 11.1 | C23: =C22*3.7 -> 11.1 | D23: V | E23: 3.7 V/cell.
A24: Motor KV | B24: 1000 | C24: 980 | D24: rpm/V | E24: Manufacturer rating.
A25: Loaded-rpm factor | B25: 0.8 | C25: 0.8 | D25: - | E25: Assumed: loaded rpm ~80% of no-load.
A26: Loaded rpm | B26: =B24*B23*B25 -> 8880 | C26: =C24*C23*C25 -> 8702.4 | D26: rpm | E26: KV x V x factor
A27: Propeller diameter | B27: 10 | C27: 10 | D27: in | E27: 10 in prop; ground clearance OK on high wing (radius 127 mm).
A28: Propeller pitch | B28: 4.7 | C28: 4.7 | D28: in
A29: Pitch speed | B29: =B28*0.0254*B26/60 -> 17.66824 | C29: =C28*0.0254*C26/60 -> 17.314875 | D29: m/s | E29: Thrust falls to ~0 as airspeed approaches this.
A30: Static thrust at full throttle (ASSUMED) | B30: 700 | C30: 850 | D30: g | E30: Robu's A2212 page claims ~700 g; R2 is an estimate. MUST be verified on a thrust rig.
A31: Static thrust-to-weight | B31: =B30/B13 -> 0.80612656 | C31: =C30/C13 -> 1.0093813 | D31: - | E31: Target >= 0.6 for hand launch, >= ~0.8 comfortable.
A32: Full-throttle current (ASSUMED) | B32: 14 | C32: 14 | D32: A | E32: 10x4.7 on 3S; verify with watt meter.
A33: Electrical power at full throttle | B33: =B23*B32 -> 155.4 | C33: =C23*C32 -> 155.4 | D33: W | E33: Motor rated ~160 W class: slightly above rating, so limit full-throttle bursts.
A34: ESC continuous rating | B34: 30 | C34: 40 | D34: A | E34: From BOM.
A35: ESC margin | B35: =B34/B32 -> 2.1428571 | C35: =C34/C32 -> 2.8571429 | D35: x | E35: Target >= 1.5x (>= 2x preferred).
A36: Battery capacity | B36: 2200 | C36: 2200 | D36: mAh | E36: From BOM.
A37: Battery C rating (continuous) | B37: 30 | C37: 40 | D37: C | E37: Manufacturer rating; treat as optimistic.
A38: Battery max continuous current | B38: =B36/1000*B37 -> 66 | C38: =C36/1000*C37 -> 88 | D38: A
A39: Battery current margin | B39: =B38/B32 -> 4.7142857 | C39: =C38/C32 -> 6.2857143 | D39: x | E39: Target >= 2x.
A40: PERFORMANCE & ENDURANCE (SIMPLIFIED MODEL)
A41: Assumed cruise lift-to-drag ratio | B41: 6 | C41: 6 | D41: - | E41: Conservative for a foam trainer.
A42: Cruise drag = W / (L/D) | B42: =B15/B41 -> 1.4197523 | C42: =C15/C41 -> 1.3768335 | D42: N
A43: Overall propulsion efficiency (battery to thrust power) | B43: 0.45 | C43: 0.45 | D43: - | E43: Assumed.
A44: Cruise electrical power | B44: =B42*B20/B43 -> 34.207091 | C44: =C42*C20/C43 -> 32.667766 | D44: W
A45: Cruise current | B45: =B44/B23 -> 3.0817199 | C45: =C44/C23 -> 2.943042 | D45: A
A46: Usable battery fraction | B46: 0.8 | C46: 0.8 | D46: - | E46: Land at ~20% remaining to protect the LiPo.
A47: Endurance, steady cruise | B47: =B36*B46/1000/B45*60 -> 34.266579 | C47: =C36*C46/1000/C45*60 -> 35.881242 | D47: min | E47: Optimistic upper bound.
A48: Average current, mixed flying (ASSUMED) | B48: 7 | C48: 7 | D48: A | E48: Climbs + manoeuvres; measure with watt meter/telemetry.
A49: Endurance, mixed flying | B49: =B36*B46/1000/B48*60 -> 15.085714 | C49: =C36*C46/1000/C48*60 -> 15.085714 | D49: min | E49: Planning figure.
A50: Best-climb airspeed (assumed) | B50: 10 | C50: 10 | D50: m/s
A51: Thrust at climb speed | B51: =B30/1000*B14*(1-B50/B29) -> 2.980365 | C51: =C30/1000*C14*(1-C50/C29) -> 3.5226986 | D51: N | E51: Linear thrust decay with airspeed (simplification).
A52: Excess thrust | B52: =B51-B42 -> 1.5606127 | C52: =C51-C42 -> 2.1458651 | D52: N | E52: Drag at climb speed taken equal to cruise drag.
A53: Rate of climb | B53: =B52*B50/B15 -> 1.8320247 | C53: =C52*C50/C15 -> 2.5975849 | D53: m/s | E53: ROC = (T-D)V/W
A54: Cruise thrust needed / static thrust | B54: =B42/(B30/1000*B14) -> 0.20675 | C54: =C42/(C30/1000*C14) -> 0.16511765 | D54: - | E54: Low value = lots of throttle headroom.
A55: Propulsion sufficiency verdict | B55: =IF(AND(B31>=0.6,B53>=1,B19<9,B35>=1.5,B39>=2),"PASS","REVIEW") -> PASS | C55: =IF(AND(C31>=0.6,C53>=1,C19<9,C35>=1.5,C39>=2),"PASS","REVIEW") -> PASS | E55: PASS if T/W>=0.6, ROC>=1 m/s, Vs<9 m/s, ESC margin>=1.5x, battery margin>=2x.
A56: WING SPAR BENDING CHECK (3 g PULL-UP)
A57: Load factor | B57: 3 | C57: 3 | D57: g
A58: Total lift at load factor | B58: =B15*B57 -> 25.555541 | C58: =C15*C57 -> 24.783003 | D58: N
A59: Root bending moment (elliptical load) | B59: =B58/2*(4/(3*PI()))*(B5/2) -> 2.9826798 | C59: =C58/2*(4/(3*PI()))*(C5/2) -> 2.8925141 | D59: N·m | E59: Half-wing, elliptical lift distribution; foam skins ignored (conservative).
A60: Spar outer diameter | B60: 6 | C60: 8 | D60: mm | E60: From BOM.
A61: Spar inner diameter | B61: 0 | C61: 6 | D61: mm | E61: 0 = solid rod.
A62: Second moment of area | B62: =PI()*(B60^4-B61^4)/64*10^-12 -> 6.3617251e-11 | C62: =PI()*(C60^4-C61^4)/64*10^-12 -> 1.3744468e-10 | D62: m⁴
A63: Bending stress | B63: =B59*(B60/2/1000)/B62/10^6 -> 140.65429 | C63: =C59*(C60/2/1000)/C62/10^6 -> 84.179734 | D63: MPa | E63: sigma = M c / I
A64: Allowable flexural stress (conservative) | B64: 600 | C64: 600 | D64: MPa | E64: Assumed for pultruded carbon rod/tube; request supplier data.
A65: Safety factor | B65: =B64/B63 -> 4.2657782 | C65: =C64/C63 -> 7.1276063 | D65: x | E65: Target >= 2 at 3 g.
A67: BATTERY CAPACITY TRADE-OFF (budget airframe, 3S 30C)
A68: Metric | B68: Option 1 | C68: Option 2 (baseline) | D68: Option 3 | E68: Note
A69: Capacity (mAh) | B69: 1500 | C69: 2200 | D69: 3000 | E69: Orange 3S options on Robu.
A70: Battery mass (g) | B70: 125 | C70: 185 | D70: 245 | E70: Approximate; confirm from datasheet.
A71: Takeoff mass (g) | B71: =(B11-BOM!L13+B70)*(1+B12) -> 805.35 | C71: =(B11-BOM!L13+C70)*(1+B12) -> 868.35 | D71: =(B11-BOM!L13+D70)*(1+B12) -> 931.35 | E71: (dry mass - baseline battery + this battery) x (1+contingency)
A72: Static thrust-to-weight | B72: =B30/B71 -> 0.86918731 | C72: =B30/C71 -> 0.80612656 | D72: =B30/D71 -> 0.75159714 | E72: Budget static thrust
A73: Wing loading (g/dm²) | B73: =B71/(B7*100) -> 33.278926 | C73: =C71/(B7*100) -> 35.882231 | D73: =D71/(B7*100) -> 38.485537
A74: Mixed-flying endurance (min) | B74: =B69*B46/1000/B48*60 -> 10.285714 | C74: =C69*B46/1000/B48*60 -> 15.085714 | D74: =D69*B46/1000/B48*60 -> 20.571429 | E74: At average current above (optimistic: ignores heavier-weight current increase)
A75: Continuous current capability at 30C (A) | B75: =B69/1000*B37 -> 45 | C75: =C69/1000*B37 -> 66 | D75: =D69/1000*B37 -> 90 | E75: Needs >> full-throttle current

Sheet Sources
A1: Sources and price basis
A3: Reference | B3: URL | C3: Use / price basis
A4: Robu – A2212 1000 KV motor (listing ₹375; claims ~700 g thrust, notes low-grade bearings/vibration) | B4: https://aws.robu.in/product/a2212-1000-kv-bldc-brushless-dc-motor-for-drone-without-soldered-connector | C4: Listing-based price
A5: Robu – A2212 1000 KV motor + SimonK 30 A ESC (ESC listed ₹342 on related page) | B5: https://aws.robu.in/?p=5933 | C5: Listing-based price (ESC)
A6: RobotShop – A2212 1000 KV spec (160 W, recommended props 1060 / 9050) | B6: https://ca.robotshop.com/products/e-s-motor-xxd-a2212-brushless-motor-160w-mounting-base-kits-kv-1000 | C6: Spec reference
A7: Robu – Orange 3S 2200 mAh 30C LiPo | B7: https://robu.in/?p=23741 | C7: Product page; price estimated – check live
A8: Robu – Orange LiPo category (30C/40C options) | B8: https://robu.in/product-category/batteries/battery/lithium-polymer-li-po | C8: Category page
A9: Probots – 3S 2200 mAh 60C (burst) LiPo | B9: https://probots.co.in/11-1v-2200mah-60c-3s-lipo-battery-lithium-polymer.html | C9: Alternative vendor
A10: Robu – FlySky FS-i6X + FS-iA10B bundle (AFHDS 2A, 6 ch Tx, 10 ch Rx) | B10: https://st.robu.in/?p=33428 | C10: Product page; price estimated (Rs ~5,500 for Tx+Rx)
A11: Probots – FlySky FS-i6X + iA10B (bind procedure, AA battery Tx) | B11: https://probots.co.in/flysky-fs-i6x-10ch-rc-transmitter-ia10b-receiver.html | C11: Product page
A12: All other items: Amazon.in / Robu search links | B12: https://www.amazon.in/ | C12: Prices are my estimates for Indian online/hobby stores; no live listing was verified. Re-check before ordering.
